pesapy/__init__.py
pesapy/account_balance.py
pesapy/b2b.py
pesapy/b2c.py
pesapy/c2b.py
pesapy/mpesa_express.py
pesapy/reversal.py
pesapy/trans_status.py
pesapy/utils/__init__.py
pesapy/utils/access_token.py
pesapy/utils/request_passwd.py
pesapy/utils/security_credentials.py
pesapy/utils/timestamp.py
pesapy/utils/validate_url.py
pesapy-0.0.3.dist-info/LICENCE
pesapy-0.0.3.dist-info/LICENSE
pesapy-0.0.3.dist-info/METADATA
pesapy-0.0.3.dist-info/WHEEL
pesapy-0.0.3.dist-info/top_level.txt
pesapy-0.0.3.dist-info/RECORD
