Metadata-Version: 2.1
Name: pesapy
Version: 0.0.3
Summary: Python Mpesa API wrapper
Home-page: https://github.com/kimengu-david/mpesa_py
Author: David Mutune
Author-email: davidmutune200@gmail.com
License: UNKNOWN
Project-URL: Bug Tracker, https://github.com/kimengu-david/mpesa_py/issues
Platform: UNKNOWN
Classifier: Programming Language :: Python :: 3
Classifier: License :: OSI Approved :: MIT License
Classifier: Operating System :: OS Independent
Requires-Python: >=3.6
Requires-Dist: pycryptodome
Requires-Dist: python-decouple
Requires-Dist: python-dotenv
Requires-Dist: requests
Requires-Dist: wheel
